{
  "main": {
    "id": "f986da1263112140",
    "type": "split",
    "children": [
      {
        "id": "39a9dd0084e7ac7c",
        "type": "tabs",
        "children": [
          {
            "id": "e661c7fe1eb353cc",
            "type": "leaf",
            "state": {
              "type": "markdown",
              "state": {
                "file": "ComputerScience/[3-2] 뉴럴네트워크/md/신경망_핵심이론_시험정리.md",
                "mode": "preview",
                "source": false
              },
              "icon": "lucide-file",
              "title": "신경망_핵심이론_시험정리"
            }
          }
        ]
      }
    ],
    "direction": "vertical"
  },
  "left": {
    "id": "e6846e88925d1f6e",
    "type": "split",
    "children": [
      {
        "id": "3690d7f713394d67",
        "type": "tabs",
        "children": [
          {
            "id": "ba9e23474eb62275",
            "type": "leaf",
            "state": {
              "type": "file-explorer",
              "state": {
                "sortOrder": "alphabeticalReverse",
                "autoReveal": false
              },
              "icon": "lucide-folder-closed",
              "title": "파일 탐색기"
            }
          },
          {
            "id": "00728ea3c734214e",
            "type": "leaf",
            "state": {
              "type": "search",
              "state": {
                "query": "",
                "matchingCase": false,
                "explainSearch": false,
                "collapseAll": false,
                "extraContext": false,
                "sortOrder": "alphabetical"
              },
              "icon": "lucide-search",
              "title": "검색"
            }
          },
          {
            "id": "1c7e08013834b2c8",
            "type": "leaf",
            "state": {
              "type": "bookmarks",
              "state": {},
              "icon": "lucide-bookmark",
              "title": "Bookmarks"
            }
          }
        ]
      }
    ],
    "direction": "horizontal",
    "width": 219.5041847229004
  },
  "right": {
    "id": "67c0be972fb46913",
    "type": "split",
    "children": [
      {
        "id": "c7d4995ae0eae292",
        "type": "tabs",
        "children": [
          {
            "id": "97d54e5193e38c04",
            "type": "leaf",
            "state": {
              "type": "backlink",
              "state": {
                "file": "ComputerScience/프로그래밍언어론/과제/3장 연습문제 (과제).md",
                "collapseAll": false,
                "extraContext": false,
                "sortOrder": "alphabetical",
                "showSearch": false,
                "searchQuery": "",
                "backlinkCollapsed": false,
                "unlinkedCollapsed": true
              },
              "icon": "links-coming-in",
              "title": "3장 연습문제 (과제) 의 백링크"
            }
          },
          {
            "id": "83d15432eceee9d1",
            "type": "leaf",
            "state": {
              "type": "outgoing-link",
              "state": {
                "file": "ComputerScience/프로그래밍언어론/과제/3장 제출용.md",
                "linksCollapsed": false,
                "unlinkedCollapsed": true
              },
              "icon": "links-going-out",
              "title": "3장 제출용 의 나가는 링크"
            }
          },
          {
            "id": "218604918d7d2429",
            "type": "leaf",
            "state": {
              "type": "tag",
              "state": {
                "sortOrder": "frequency",
                "useHierarchy": true,
                "showSearch": false,
                "searchQuery": ""
              },
              "icon": "lucide-tags",
              "title": "태그"
            }
          },
          {
            "id": "9d5499165d9fbe00",
            "type": "leaf",
            "state": {
              "type": "outline",
              "state": {
                "file": "ComputerScience/[3-2] 뉴럴네트워크/md/신경망_핵심이론_시험정리.md",
                "followCursor": false,
                "showSearch": false,
                "searchQuery": ""
              },
              "icon": "lucide-list",
              "title": "신경망_핵심이론_시험정리 의 개요"
            }
          }
        ],
        "currentTab": 3
      }
    ],
    "direction": "horizontal",
    "width": 300
  },
  "left-ribbon": {
    "hiddenItems": {
      "switcher:빠른 전환기 열기": false,
      "graph:그래프 뷰 열기": false,
      "canvas:새 캔버스 만들기": false,
      "daily-notes:오늘의 일일 노트 열기": false,
      "templates:템플릿 삽입": false,
      "command-palette:명령어 팔레트 열기": false,
      "bases:새 베이스 생성하기": false,
      "pdf-plus:PDF++: Toggle auto-copy": false,
      "pdf-plus:PDF++: Toggle auto-focus": false,
      "pdf-plus:PDF++: Toggle auto-paste": false,
      "mermaid-tools:Open Mermaid Toolbar": false,
      "obsidian-git:Open Git source control": false
    }
  },
  "active": "e661c7fe1eb353cc",
  "lastOpenFiles": [
    "ComputerScience/[3-2] 뉴럴네트워크/pdf/2장_퍼셉트론.pdf",
    "ComputerScience/[3-2] 뉴럴네트워크/pdf/3장_인공신경망.pdf",
    "ComputerScience/[3-2] 뉴럴네트워크/pdf/AIE309_4장_신경망학습.pdf",
    "ComputerScience/[3-2] 뉴럴네트워크/pdf/AIE309_5장_오차역전파.pdf",
    "ComputerScience/[3-2] 뉴럴네트워크/md/신경망_핵심이론_시험정리.md",
    "ComputerScience/[3-2] 최적화수학/1. Matrix/1. Matrix.md",
    "ComputerScience/[3-2] 최적화수학/1. Matrix/MSC087_1장_행렬_v3.pdf",
    "ComputerScience/[3-2] 컴퓨터 그래픽스/middle exam.md",
    "ComputerScience/[3-2] 컴퓨터 그래픽스/0. 소개.md",
    "ComputerScience/[3-2] 컴퓨터 그래픽스/README.md",
    "스크린샷 2025-05-07 091243.png",
    "2024-2+중간고사+시간표_업로드용_변동.pdf",
    "[공지용]+2024-2+기말고사+시간표.pdf",
    "Obsidian/KR_history/고대/남북국시대/통일신라.md",
    "Obsidian/KR_history/고대/삼국시대/백제.md",
    "Obsidian/KR_history/고대/삼국시대/신라.md",
    "Obsidian/KR_history/고대/삼국시대/고구려.md",
    "Obsidian/KR_history/고대/삼국시대/가야.md",
    "Obsidian/KR_history/고대/남북국시대/발해.md",
    "Obsidian/KR_history/고려/초기 정치.md",
    "Obsidian/KR_history/고려/중기 정치.md",
    "Obsidian/KR_history/고려/외교.md",
    "Obsidian/KR_history/고대/삼국시대",
    "Obsidian/KR_history/고대/남북국시대",
    "Obsidian/KR_history/고대/문화.md",
    "Obsidian/KR_history/고대/경제 + 사회.md",
    "Obsidian/KR_history/선사시대.md",
    "Obsidian/KR_history/고려",
    "Obsidian/KR_history/고대 이전.md",
    "Obsidian/KR_history/고대",
    "Obsidian/constellation/출생천도궁.png",
    "AGENTS.md",
    "ComputerScience/[3-1] 프로그래밍언어론/과제/5장 연습문제 (제출용).md",
    "Pasted image 20250924155841.png",
    "고ㅏ제.md",
    "ComputerScience/[3-2] 빅데이터분석/Converted_MD/07-PandasSeries.md",
    "ComputerScience/[3-2] 빅데이터분석/Converted_MD/06-SparkDataFrames.md",
    "ComputerScience/융합전공/프로젝트 주제.md",
    "프로젝트/오픈소스.md",
    "image/IMG_1555.jpg",
    "image/Pasted image 20250919191502.png",
    "image/Pasted image 20250919191005.png",
    "image/Pasted image 20250919190544.png",
    "image/Pasted image 20250919190047.png",
    "image/Pasted image 20250919185534.png",
    "image/Pasted image 20250919184828.png"
  ]
}